[
{
"Rate": 73.7,
"School": 312
},
{
"Rate": 68.5,
"School": 21088
},
{
"Rate": 63.3,
"School": 446
},
{
"Rate": 61.7,
"School": 619
},
{
"Rate": 62.6,
"School": 866
},
{
"Rate": 64.2,
"School": 17691
},
{
"Rate": 64.6,
"School": 5402
},
{
"Rate": 60.5,
"School": 2082
},
{
"Rate": 63.8,
"School": 658
},
{
"Rate": 59.1,
"School": 67
},
{
"Rate": 59.7,
"School": 965
},
{
"Rate": 62.8,
"School": 137
},
{
"Rate": 61.9,
"School": 114
},
{
"Rate": 58.5,
"School": 3550
},
{
"Rate": 60.3,
"School": 1713
},
{
"Rate": 59.3,
"School": 4891
},
{
"Rate": 58,
"School": 6866
},
{
"Rate": 60.7,
"School": 11159
},
{
"Rate": 60.6,
"School": 345
},
{
"Rate": 54,
"School": 535
},
{
"Rate": 56,
"School": 419
},
{
"Rate": 56.9,
"School": 81
},
{
"Rate": 55.3,
"School": 3482
},
{
"Rate": 54.7,
"School": 2075
},
{
"Rate": 60,
"School": 923
},
{
"Rate": 52.6,
"School": 4067
},
{
"Rate": 55.7,
"School": 292
},
{
"Rate": 60.7,
"School": 662
},
{
"Rate": 55,
"School": 1004
},
{
"Rate": 59.6,
"School": 486
},
{
"Rate": 55.6,
"School": 62323
},
{
"Rate": 56.7,
"School": 2421
},
{
"Rate": 55.9,
"School": 22057
},
{
"Rate": 54.5,
"School": 2905
},
{
"Rate": 57.1,
"School": 699
},
{
"Rate": 52.3,
"School": 7434
},
{
"Rate": 51.7,
"School": 16037
},
{
"Rate": 54,
"School": 4306
},
{
"Rate": 53.5,
"School": 13544
},
{
"Rate": 46.1,
"School": 2052
},
{
"Rate": 47.8,
"School": 3657
},
{
"Rate": 51,
"School": 4432
},
{
"Rate": 48.9,
"School": 5334
},
{
"Rate": 44.3,
"School": 4552
},
{
"Rate": 53.3,
"School": 1622
}
]